mkdocs_simple_hooks/__init__.py
mkdocs_simple_hooks-0.1.4.dist-info/LICENSE
mkdocs_simple_hooks-0.1.4.dist-info/METADATA
mkdocs_simple_hooks-0.1.4.dist-info/WHEEL
mkdocs_simple_hooks-0.1.4.dist-info/entry_points.txt
mkdocs_simple_hooks-0.1.4.dist-info/top_level.txt
mkdocs_simple_hooks-0.1.4.dist-info/RECORD
