Metadata-Version: 2.1
Name: mkdocs-simple-hooks
Version: 0.1.4
Summary: Define your own hooks for mkdocs, without having to create a new package.
Home-page: https://github.com/aklajnert/mkdocs-simple-hooks
Author: Andrzej Klajnert
Author-email: python@aklajnert.pl
License: MIT
Platform: UNKNOWN
Classifier: Programming Language :: Python :: 3
Classifier: Programming Language :: Python :: 3.6
Classifier: Programming Language :: Python :: 3.7
Classifier: Programming Language :: Python :: 3.8
Classifier: Programming Language :: Python :: 3.9
Classifier: Programming Language :: Python :: 3.10
Classifier: License :: OSI Approved :: MIT License
Classifier: Operating System :: OS Independent
Classifier: Intended Audience :: Developers
Classifier: Topic :: Documentation
License-File: LICENSE
Requires-Dist: mkdocs (>=1)
Provides-Extra: test
Requires-Dist: pytest (>=4.0) ; extra == 'test'
Requires-Dist: pytest-cov ; extra == 'test'
